ze_prompter/__init__.py
ze_prompter/cli.py
ze_prompter/manager.py
ze_prompter/api/__init__.py
ze_prompter/api/dependencies.py
ze_prompter/api/main.py
ze_prompter/api/routes/__init__.py
ze_prompter/api/routes/auth.py
ze_prompter/api/routes/models.py
ze_prompter/api/routes/prompts.py
ze_prompter/core/__init__.py
ze_prompter/core/auth.py
ze_prompter/core/model_manager.py
ze_prompter/core/prompt_manager.py
ze_prompter/dashboard/__init__.py
ze_prompter/dashboard/templates/base.html
ze_prompter/dashboard/templates/dashboard.html
ze_prompter/dashboard/templates/login.html
ze_prompter/dashboard/templates/models.html
ze_prompter/dashboard/templates/prompts.html
ze_prompter/models/__init__.py
ze_prompter/models/database.py
ze_prompter/models/model.py
ze_prompter/models/prompt_template.py
ze_prompter/models/user.py
ze_prompter-0.1.0.data/scripts/run_server.py
ze_prompter-0.1.0.dist-info/METADATA
ze_prompter-0.1.0.dist-info/WHEEL
ze_prompter-0.1.0.dist-info/entry_points.txt
ze_prompter-0.1.0.dist-info/top_level.txt
ze_prompter-0.1.0.dist-info/RECORD
