Metadata-Version: 2.4
Name: ze-prompter
Version: 0.1.0
Summary: A library for managing prompt templates with versioning and AI models
Home-page: https://github.com/olsihoxha/zeprompter
Author: Olsi Hoxha
Author-email: olsihoxha824@gmail.com
Project-URL: Bug Reports, https://github.com/olsihoxha/zeprompter/issues
Project-URL: Source, https://github.com/olsihoxha/zeprompter
Keywords: prompt templates,ai,machine learning,versioning,fastapi,web interface
Classifier: Development Status :: 3 - Alpha
Classifier: Intended Audience :: Developers
Classifier: Topic :: Software Development :: Libraries :: Python Modules
Classifier: Topic :: Scientific/Engineering :: Artificial Intelligence
Classifier: License :: OSI Approved :: MIT License
Classifier: Operating System :: OS Independent
Classifier: Programming Language :: Python :: 3
Classifier: Programming Language :: Python :: 3.8
Classifier: Programming Language :: Python :: 3.9
Classifier: Programming Language :: Python :: 3.10
Classifier: Programming Language :: Python :: 3.11
Requires-Python: >=3.8
Requires-Dist: annotated-types==0.7.0
Requires-Dist: anyio==4.9.0
Requires-Dist: bcrypt==4.3.0
Requires-Dist: certifi==2025.7.14
Requires-Dist: charset-normalizer==3.4.2
Requires-Dist: click==8.2.1
Requires-Dist: ecdsa==0.19.1
Requires-Dist: fastapi==0.116.1
Requires-Dist: h11==0.16.0
Requires-Dist: idna==3.10
Requires-Dist: Jinja2==3.1.6
Requires-Dist: MarkupSafe==3.0.2
Requires-Dist: passlib==1.7.4
Requires-Dist: pyasn1==0.6.1
Requires-Dist: pydantic==2.11.7
Requires-Dist: pydantic_core==2.33.2
Requires-Dist: python-jose==3.5.0
Requires-Dist: python-multipart==0.0.20
Requires-Dist: requests==2.32.4
Requires-Dist: rsa==4.9.1
Requires-Dist: setuptools==80.9.0
Requires-Dist: six==1.17.0
Requires-Dist: sniffio==1.3.1
Requires-Dist: SQLAlchemy==2.0.41
Requires-Dist: starlette==0.47.2
Requires-Dist: typing-inspection==0.4.1
Requires-Dist: typing_extensions==4.14.1
Requires-Dist: urllib3==2.5.0
Requires-Dist: uvicorn==0.35.0
Dynamic: author
Dynamic: author-email
Dynamic: classifier
Dynamic: description
Dynamic: description-content-type
Dynamic: home-page
Dynamic: keywords
Dynamic: project-url
Dynamic: requires-dist
Dynamic: requires-python
Dynamic: summary
